ZoeDePythonXingjiZhilv/README.md
ZoeDePythonXingjiZhilv/__init__.py
ZoeDePythonXingjiZhilv/__main__.py
ZoeDePythonXingjiZhilv/file.epub
ZoeDePythonXingjiZhilv/index.html
ZoeDePythonXingjiZhilv/css/__init__.py
ZoeDePythonXingjiZhilv/css/annotations.css
ZoeDePythonXingjiZhilv/css/main.css
ZoeDePythonXingjiZhilv/css/normalize.css
ZoeDePythonXingjiZhilv/css/popup.css
ZoeDePythonXingjiZhilv/font/__init__.py
ZoeDePythonXingjiZhilv/font/fontello.eot
ZoeDePythonXingjiZhilv/font/fontello.svg
ZoeDePythonXingjiZhilv/font/fontello.ttf
ZoeDePythonXingjiZhilv/font/fontello.woff
ZoeDePythonXingjiZhilv/img/__init__.py
ZoeDePythonXingjiZhilv/img/annotator-glyph-sprite.png
ZoeDePythonXingjiZhilv/img/annotator-icon-sprite.png
ZoeDePythonXingjiZhilv/img/apple-touch-icon.png
ZoeDePythonXingjiZhilv/img/cancelfullscreen.png
ZoeDePythonXingjiZhilv/img/close.png
ZoeDePythonXingjiZhilv/img/fullscreen.png
ZoeDePythonXingjiZhilv/img/loader.gif
ZoeDePythonXingjiZhilv/img/menu-icon.png
ZoeDePythonXingjiZhilv/img/save.png
ZoeDePythonXingjiZhilv/img/saved.png
ZoeDePythonXingjiZhilv/img/settings-s.png
ZoeDePythonXingjiZhilv/img/settings.png
ZoeDePythonXingjiZhilv/img/star.png
ZoeDePythonXingjiZhilv/js/__init__.py
ZoeDePythonXingjiZhilv/js/epub.js
ZoeDePythonXingjiZhilv/js/epub.min.js
ZoeDePythonXingjiZhilv/js/epub.min.map
ZoeDePythonXingjiZhilv/js/hooks.min.js
ZoeDePythonXingjiZhilv/js/hooks.min.map
ZoeDePythonXingjiZhilv/js/reader.js
ZoeDePythonXingjiZhilv/js/reader.js.map
ZoeDePythonXingjiZhilv/js/reader.min.js
ZoeDePythonXingjiZhilv/js/reader.min.map
ZoeDePythonXingjiZhilv/js/hooks/__init__.py
ZoeDePythonXingjiZhilv/js/hooks/extensions/__init__.py
ZoeDePythonXingjiZhilv/js/hooks/extensions/highlight.js
ZoeDePythonXingjiZhilv/js/libs/__init__.py
ZoeDePythonXingjiZhilv/js/libs/jquery.min.js
ZoeDePythonXingjiZhilv/js/libs/localforage.min.js
ZoeDePythonXingjiZhilv/js/libs/screenfull.js
ZoeDePythonXingjiZhilv/js/libs/screenfull.min.js
ZoeDePythonXingjiZhilv/js/libs/zip.min.js
zoe_de_python_xingji_zhilv-2024.3.3.0.dist-info/METADATA
zoe_de_python_xingji_zhilv-2024.3.3.0.dist-info/WHEEL
zoe_de_python_xingji_zhilv-2024.3.3.0.dist-info/entry_points.txt
zoe_de_python_xingji_zhilv-2024.3.3.0.dist-info/top_level.txt
zoe_de_python_xingji_zhilv-2024.3.3.0.dist-info/RECORD
